{"file":"final-sentence-stamps.png","frames":{
"stamps_8":{"x":285,"y":194,"w":93,"h":95,"offX":3,"offY":0,"sourceW":98,"sourceH":95},
"stamps_9":{"x":190,"y":194,"w":93,"h":95,"offX":3,"offY":0,"sourceW":99,"sourceH":95},
"stamps_10":{"x":95,"y":194,"w":93,"h":95,"offX":2,"offY":0,"sourceW":98,"sourceH":95},
"stamps_11":{"x":0,"y":194,"w":93,"h":95,"offX":2,"offY":0,"sourceW":98,"sourceH":95},
"stamps_12":{"x":380,"y":97,"w":93,"h":95,"offX":2,"offY":0,"sourceW":98,"sourceH":95},
"stamps_13":{"x":285,"y":97,"w":93,"h":95,"offX":3,"offY":0,"sourceW":99,"sourceH":95},
"stamps_14":{"x":190,"y":97,"w":93,"h":95,"offX":2,"offY":0,"sourceW":98,"sourceH":95},
"stamps_1":{"x":95,"y":97,"w":93,"h":95,"offX":3,"offY":0,"sourceW":98,"sourceH":95},
"stamps_2":{"x":0,"y":97,"w":93,"h":95,"offX":3,"offY":0,"sourceW":99,"sourceH":95},
"stamps_3":{"x":380,"y":0,"w":93,"h":95,"offX":2,"offY":0,"sourceW":98,"sourceH":95},
"stamps_4":{"x":285,"y":0,"w":93,"h":95,"offX":3,"offY":0,"sourceW":98,"sourceH":95},
"stamps_5":{"x":190,"y":0,"w":93,"h":95,"offX":3,"offY":0,"sourceW":98,"sourceH":95},
"stamps_6":{"x":95,"y":0,"w":93,"h":95,"offX":3,"offY":0,"sourceW":99,"sourceH":95},
"stamps_7":{"x":0,"y":0,"w":93,"h":95,"offX":2,"offY":0,"sourceW":98,"sourceH":95}}}